whistic/__init__.py
whistic/vendorintakeform.py
whistic/vendors.py
whistic/whistic.py
whistic-0.3.0.dist-info/licenses/LICENSE
whistic-0.3.0.dist-info/METADATA
whistic-0.3.0.dist-info/WHEEL
whistic-0.3.0.dist-info/top_level.txt
whistic-0.3.0.dist-info/RECORD
