Metadata-Version: 2.4
Name: whistic
Version: 0.3.0
Summary: Python SDK to interface with the Whistic API
Home-page: https://github.com/massyn/whistic
Author: Phil Massyn
Author-email: Phil Massyn <phil.massyn@icloud.com>
Maintainer-email: Phil Massyn <phil.massyn@icloud.com>
License: MIT License
Project-URL: Homepage, https://github.com/massyn/whistic
Project-URL: Bug Tracker, https://github.com/massyn/whistic/issues
Project-URL: Documentation, https://github.com/massyn/whistic#readme
Project-URL: Source Code, https://github.com/massyn/whistic
Keywords: whistic,api,sdk,vendor,management,third-party,risk
Classifier: Development Status :: 4 - Beta
Classifier: Intended Audience :: Developers
Classifier: License :: OSI Approved :: MIT License
Classifier: Operating System :: OS Independent
Classifier: Programming Language :: Python :: 3
Classifier: Programming Language :: Python :: 3.7
Classifier: Programming Language :: Python :: 3.8
Classifier: Programming Language :: Python :: 3.9
Classifier: Programming Language :: Python :: 3.10
Classifier: Programming Language :: Python :: 3.11
Classifier: Programming Language :: Python :: 3.12
Classifier: Topic :: Software Development :: Libraries :: Python Modules
Classifier: Topic :: Internet :: WWW/HTTP :: HTTP Servers
Classifier: Topic :: Security
Requires-Python: >=3.7
License-File: LICENSE
Requires-Dist: requests>=2.25.0
Requires-Dist: python-dotenv>=0.19.0
Requires-Dist: colorama>=0.4.4
Dynamic: author
Dynamic: home-page
Dynamic: license-file
Dynamic: requires-python
